preflexpart/__init__.py
preflexpart/cli.py
preflexpart/data_loading.py
preflexpart/input_fields.py
preflexpart/logging_config.py
preflexpart/operators.py
preflexpart/preprocessing.py
preflexpart/runner.py
preflexpart/xarray_to_grib.py
preflexpart-0.1.2.dist-info/LICENSE
preflexpart-0.1.2.dist-info/METADATA
preflexpart-0.1.2.dist-info/WHEEL
preflexpart-0.1.2.dist-info/RECORD
